{
  "@type": "job",
  "@href": "/v3/job/239442106",
  "@representation": "standard",
  "@permissions": {
    "read": true,
    "delete_log": false,
    "debug": false,
    "cancel": false,
    "restart": false
  },
  "id": 239442106,
  "allow_failure": false,
  "number": "16866.7",
  "state": "passed",
  "started_at": "2017-06-05T01:39:33Z",
  "finished_at": "2017-06-05T02:31:15Z",
  "build": {
    "@type": "build",
    "@href": "/v3/build/239442099",
    "@representation": "minimal",
    "id": 239442099,
    "number": "16866",
    "state": "failed",
    "duration": 31460,
    "event_type": "pull_request",
    "previous_state": "failed",
    "pull_request_title": "[FLINK-6488] [scripts] Remove 'start-local.sh' script",
    "pull_request_number": 4074,
    "started_at": "2017-06-05T01:39:31Z",
    "finished_at": "2017-06-05T02:56:40Z",
    "private": false
  },
  "queue": "builds.docker",
  "repository": {
    "@type": "repository",
    "@href": "/v3/repo/2476141",
    "@representation": "minimal",
    "id": 2476141,
    "name": "flink",
    "slug": "apache/flink"
  },
  "commit": {
    "@type": "commit",
    "@representation": "minimal",
    "id": 69419066,
    "sha": "7a7e95c9a0b71960383ac41669bfccf609b9b3e8",
    "ref": "refs/pull/4074/merge",
    "message": "[FLINK-6488] [scripts] Remove 'start-local.sh' script",
    "compare_url": "https://github.com/apache/flink/pull/4074",
    "committed_at": "2017-06-05T01:38:04Z"
  },
  "owner": {
    "@type": "organization",
    "@href": "/v3/org/440",
    "@representation": "minimal",
    "id": 440,
    "login": "apache"
  },
  "stage": null,
  "created_at": "2017-06-05T01:39:27.607Z",
  "updated_at": "2018-06-02T13:57:43.095Z",
  "private": false
}