{
  "@type": "job",
  "@href": "/v3/job/278650499",
  "@representation": "standard",
  "@permissions": {
    "read": true,
    "delete_log": false,
    "debug": false,
    "cancel": false,
    "restart": false
  },
  "id": 278650499,
  "allow_failure": false,
  "number": "7327.5",
  "state": "failed",
  "started_at": "2017-09-22T14:46:25Z",
  "finished_at": "2017-09-22T15:16:42Z",
  "build": {
    "@type": "build",
    "@href": "/v3/build/278650492",
    "@representation": "minimal",
    "id": 278650492,
    "number": "7327",
    "state": "failed",
    "duration": 5014,
    "event_type": "push",
    "previous_state": "passed",
    "pull_request_title": null,
    "pull_request_number": null,
    "started_at": "2017-09-22T14:46:18Z",
    "finished_at": "2017-09-22T15:16:42Z",
    "private": false
  },
  "queue": "builds.gce",
  "repository": {
    "@type": "repository",
    "@href": "/v3/repo/1501298",
    "@representation": "minimal",
    "id": 1501298,
    "name": "storm",
    "slug": "apache/storm"
  },
  "commit": {
    "@type": "commit",
    "@representation": "minimal",
    "id": 81245990,
    "sha": "8e90ffc2bff714aaa945d24620fb3154d264127a",
    "ref": "refs/heads/master",
    "message": "Merge branch 'master' of https://github.com/xiaoyong03/storm into STORM-2750-merge",
    "compare_url": "https://github.com/apache/storm/compare/66ff5fd9400a...8e90ffc2bff7",
    "committed_at": "2017-09-22T14:44:12Z"
  },
  "owner": {
    "@type": "organization",
    "@href": "/v3/org/440",
    "@representation": "minimal",
    "id": 440,
    "login": "apache"
  },
  "stage": null,
  "created_at": "2017-09-22T14:45:37.240Z",
  "updated_at": "2018-06-03T04:24:28.334Z",
  "private": false
}