{
  "@type": "job",
  "@href": "/v3/job/345442889",
  "@representation": "standard",
  "@permissions": {
    "read": true,
    "delete_log": false,
    "debug": false,
    "cancel": false,
    "restart": false
  },
  "id": 345442889,
  "allow_failure": false,
  "number": "191.1",
  "state": "failed",
  "started_at": "2018-02-23T21:26:06Z",
  "finished_at": "2018-02-23T21:27:01Z",
  "build": {
    "@type": "build",
    "@href": "/v3/build/345442888",
    "@representation": "minimal",
    "id": 345442888,
    "number": "191",
    "state": "failed",
    "duration": 124,
    "event_type": "pull_request",
    "previous_state": "passed",
    "pull_request_title": "WIP Refactor filters",
    "pull_request_number": 43,
    "started_at": "2018-02-23T21:26:06Z",
    "finished_at": "2018-02-23T21:27:37Z",
    "private": false
  },
  "queue": "builds.ec2",
  "repository": {
    "@type": "repository",
    "@href": "/v3/repo/17200456",
    "@representation": "minimal",
    "id": 17200456,
    "name": "uportal-messaging",
    "slug": "UW-Madison-DoIT/uportal-messaging"
  },
  "commit": {
    "@type": "commit",
    "@representation": "minimal",
    "id": 102738114,
    "sha": "f45eb1ce2151879e6ad8cb5c1218fbcafa3eba36",
    "ref": "refs/pull/43/merge",
    "message": "Merge branch 'master' into refactor",
    "compare_url": "https://github.com/UW-Madison-DoIT/uportal-messaging/pull/43",
    "committed_at": "2018-02-23T21:25:54Z"
  },
  "owner": {
    "@type": "organization",
    "@href": "/v3/org/17600",
    "@representation": "minimal",
    "id": 17600,
    "login": "UW-Madison-DoIT"
  },
  "stage": null,
  "created_at": "2018-02-23T21:26:03.442Z",
  "updated_at": "2018-06-04T05:13:37.624Z",
  "private": false
}