{
  "@type": "job",
  "@href": "/v3/job/359219807",
  "@representation": "standard",
  "@permissions": {
    "read": true,
    "delete_log": false,
    "debug": false,
    "cancel": false,
    "restart": false
  },
  "id": 359219807,
  "allow_failure": false,
  "number": "2938.1",
  "state": "failed",
  "started_at": "2018-03-28T06:01:17Z",
  "finished_at": "2018-03-28T06:13:15Z",
  "build": {
    "@type": "build",
    "@href": "/v3/build/359219806",
    "@representation": "minimal",
    "id": 359219806,
    "number": "2938",
    "state": "failed",
    "duration": 718,
    "event_type": "push",
    "previous_state": "failed",
    "pull_request_title": null,
    "pull_request_number": null,
    "started_at": "2018-03-28T06:01:17Z",
    "finished_at": "2018-03-28T06:13:15Z",
    "private": false
  },
  "queue": "builds.ec2",
  "repository": {
    "@type": "repository",
    "@href": "/v3/repo/10431477",
    "@representation": "minimal",
    "id": 10431477,
    "name": "mycore",
    "slug": "MyCoRe-Org/mycore"
  },
  "commit": {
    "@type": "commit",
    "@representation": "minimal",
    "id": 107072113,
    "sha": "c880533c81f4d3b8e0d40c453826c0e69ad48141",
    "ref": "refs/heads/master",
    "message": "Merge branch '2017.06.0.x'\n\n* 2017.06.0.x:\n  MCR-1660 fix fullscreen for classeditor\n  MCR-1807 fixed session handling\n  MCR-1819 support SOLR 'fl' parameter with MCRQL forms (#537)\n  MCR-1825 auto close inputstreams",
    "compare_url": "https://github.com/MyCoRe-Org/mycore/compare/d8781c99e2b8...c880533c81f4",
    "committed_at": "2018-03-28T06:00:41Z"
  },
  "owner": {
    "@type": "organization",
    "@href": "/v3/org/174007",
    "@representation": "minimal",
    "id": 174007,
    "login": "MyCoRe-Org"
  },
  "stage": null,
  "created_at": "2018-03-28T06:01:13.642Z",
  "updated_at": "2018-06-04T10:33:58.362Z",
  "private": false
}