{
  "@type": "job",
  "@href": "/v3/job/282059196",
  "@representation": "standard",
  "@permissions": {
    "read": true,
    "delete_log": false,
    "debug": false,
    "cancel": false,
    "restart": false
  },
  "id": 282059196,
  "allow_failure": false,
  "number": "13277.4",
  "state": "passed",
  "started_at": "2017-10-02T00:15:50Z",
  "finished_at": "2017-10-02T00:49:48Z",
  "build": {
    "@type": "build",
    "@href": "/v3/build/282059192",
    "@representation": "minimal",
    "id": 282059192,
    "number": "13277",
    "state": "failed",
    "duration": 3684,
    "event_type": "pull_request",
    "previous_state": "failed",
    "pull_request_title": "Refactor ColumnSelectorFactory; Rely on ColumnValueSelector's polymorphism",
    "pull_request_number": 4886,
    "started_at": "2017-10-02T00:14:50Z",
    "finished_at": "2017-10-02T00:49:48Z",
    "private": false
  },
  "queue": "builds.gce",
  "repository": {
    "@type": "repository",
    "@href": "/v3/repo/578446",
    "@representation": "minimal",
    "id": 578446,
    "name": "incubator-druid",
    "slug": "apache/incubator-druid"
  },
  "commit": {
    "@type": "commit",
    "@representation": "minimal",
    "id": 82316823,
    "sha": "6a16e7f754bfcf4bda7d51b366d93ecbcd89db5c",
    "ref": "refs/pull/4886/merge",
    "message": "Merge remote-tracking branch 'upstream/master' into refactor-column-selector-factory",
    "compare_url": "https://github.com/druid-io/druid/pull/4886",
    "committed_at": "2017-10-02T00:14:25Z"
  },
  "owner": {
    "@type": "organization",
    "@href": "/v3/org/61822",
    "@representation": "minimal",
    "id": 61822,
    "login": "druid-io"
  },
  "stage": null,
  "created_at": "2017-10-02T00:14:46.707Z",
  "updated_at": "2018-06-03T05:32:34.695Z",
  "private": false
}