{
  "@type": "job",
  "@href": "/v3/job/418330481",
  "@representation": "standard",
  "@permissions": {
    "read": true,
    "delete_log": false,
    "debug": false,
    "cancel": false,
    "restart": false
  },
  "id": 418330481,
  "allow_failure": false,
  "number": "46.1",
  "state": "failed",
  "started_at": "2018-08-20T17:12:49Z",
  "finished_at": "2018-08-20T17:14:09Z",
  "build": {
    "@type": "build",
    "@href": "/v3/build/418330480",
    "@representation": "minimal",
    "id": 418330480,
    "number": "46",
    "state": "failed",
    "duration": 169,
    "event_type": "push",
    "previous_state": "passed",
    "pull_request_title": null,
    "pull_request_number": null,
    "started_at": "2018-08-20T17:12:49Z",
    "finished_at": "2018-08-20T17:14:31Z",
    "private": false
  },
  "queue": "builds.gce",
  "repository": {
    "@type": "repository",
    "@href": "/v3/repo/3716539",
    "@representation": "minimal",
    "id": 3716539,
    "name": "vertx-rabbitmq-client",
    "slug": "vert-x3/vertx-rabbitmq-client"
  },
  "commit": {
    "@type": "commit",
    "@representation": "minimal",
    "id": 125681271,
    "sha": "f55a075d56e6292a9f7779d4c5b7b625fb40b631",
    "ref": "refs/heads/master",
    "message": "Implement read stream fetch",
    "compare_url": "https://github.com/vert-x3/vertx-rabbitmq-client/compare/3a443204174b...f55a075d56e6",
    "committed_at": "2018-08-20T17:12:03Z"
  },
  "owner": {
    "@type": "organization",
    "@href": "/v3/org/91111",
    "@representation": "minimal",
    "id": 91111,
    "login": "vert-x3"
  },
  "stage": null,
  "created_at": "2018-08-20T17:12:17.439Z",
  "updated_at": "2018-08-20T17:14:09.742Z",
  "private": false
}