{
  "@type": "job",
  "@href": "/v3/job/232063719",
  "@representation": "standard",
  "@permissions": {
    "read": true,
    "delete_log": false,
    "debug": false,
    "cancel": false,
    "restart": false
  },
  "id": 232063719,
  "allow_failure": false,
  "number": "1894.1",
  "state": "failed",
  "started_at": "2017-05-14T10:34:06Z",
  "finished_at": "2017-05-14T10:35:44Z",
  "build": {
    "@type": "build",
    "@href": "/v3/build/232063718",
    "@representation": "minimal",
    "id": 232063718,
    "number": "1894",
    "state": "failed",
    "duration": 98,
    "event_type": "push",
    "previous_state": "failed",
    "pull_request_title": null,
    "pull_request_number": null,
    "started_at": "2017-05-14T10:34:06Z",
    "finished_at": "2017-05-14T10:35:44Z",
    "private": false
  },
  "queue": "builds.docker",
  "repository": {
    "@type": "repository",
    "@href": "/v3/repo/4308286",
    "@representation": "minimal",
    "id": 4308286,
    "name": "blynk-server",
    "slug": "blynkkk/blynk-server"
  },
  "commit": {
    "@type": "commit",
    "@representation": "minimal",
    "id": 67176867,
    "sha": "701472b6bbd00a2bd0805053ec73f81146ec77a2",
    "ref": "refs/heads/master",
    "message": "chaining for pipeline initializer",
    "compare_url": "https://github.com/blynkkk/blynk-server/compare/9f0f0467a299...701472b6bbd0",
    "committed_at": "2017-05-14T10:33:53Z"
  },
  "owner": {
    "@type": "user",
    "@href": "/v3/user/133676",
    "@representation": "minimal",
    "id": 133676,
    "login": "blynkkk"
  },
  "stage": null,
  "created_at": "2017-05-14T10:34:05.230Z",
  "updated_at": "2018-06-02T11:10:11.351Z",
  "private": false
}