{
  "@type": "job",
  "@href": "/v3/job/250654493",
  "@representation": "standard",
  "@permissions": {
    "read": true,
    "delete_log": false,
    "debug": false,
    "cancel": false,
    "restart": false
  },
  "id": 250654493,
  "allow_failure": false,
  "number": "363.3",
  "state": "failed",
  "started_at": "2017-07-06T07:13:47Z",
  "finished_at": "2017-07-06T07:15:44Z",
  "build": {
    "@type": "build",
    "@href": "/v3/build/250654490",
    "@representation": "minimal",
    "id": 250654490,
    "number": "363",
    "state": "failed",
    "duration": 361,
    "event_type": "push",
    "previous_state": "failed",
    "pull_request_title": null,
    "pull_request_number": null,
    "started_at": "2017-07-06T07:13:46Z",
    "finished_at": "2017-07-06T07:15:44Z",
    "private": false
  },
  "queue": "builds.ec2",
  "repository": {
    "@type": "repository",
    "@href": "/v3/repo/69778",
    "@representation": "minimal",
    "id": 69778,
    "name": "commons-compress",
    "slug": "apache/commons-compress"
  },
  "commit": {
    "@type": "commit",
    "@representation": "minimal",
    "id": 72808674,
    "sha": "41afb1d762d0f22ecc5a46bb4a548d290fdeae07",
    "ref": "refs/heads/master",
    "message": "add missing license headers",
    "compare_url": "https://github.com/apache/commons-compress/compare/71f360905e17...41afb1d762d0",
    "committed_at": "2017-07-06T07:13:12Z"
  },
  "owner": {
    "@type": "organization",
    "@href": "/v3/org/440",
    "@representation": "minimal",
    "id": 440,
    "login": "apache"
  },
  "stage": null,
  "created_at": "2017-07-06T07:13:41.814Z",
  "updated_at": "2018-06-02T17:55:13.943Z",
  "private": false
}