{
  "@type": "build",
  "@href": "/v3/build/235598628",
  "@representation": "standard",
  "@permissions": {
    "read": true,
    "cancel": false,
    "restart": false
  },
  "id": 235598628,
  "number": "668",
  "state": "failed",
  "duration": 2143,
  "event_type": "push",
  "previous_state": "passed",
  "pull_request_title": null,
  "pull_request_number": null,
  "started_at": "2017-05-24T11:26:34.000Z",
  "finished_at": "2017-05-24T11:37:55.000Z",
  "private": false,
  "repository": {
    "@type": "repository",
    "@href": "/v3/repo/25241",
    "@representation": "minimal",
    "id": 25241,
    "name": "spring-data-mongodb",
    "slug": "spring-projects/spring-data-mongodb"
  },
  "branch": {
    "@type": "branch",
    "@href": "/v3/repo/25241/branch/1.10.x",
    "@representation": "minimal",
    "name": "1.10.x"
  },
  "tag": null,
  "commit": {
    "@type": "commit",
    "@representation": "minimal",
    "id": 68259359,
    "sha": "dda91f9d48865e0ec04c0e66fcf02ad8681ebe4a",
    "ref": "refs/heads/1.10.x",
    "message": "DATAMONGO-1699 - Upgrade travis-ci build to use MongoDB 3.4 server.\n\nWe now do it explicitly as there seems to be almost no movement getting the alias on the whitelist.",
    "compare_url": "https://github.com/spring-projects/spring-data-mongodb/compare/d32afee0e0c5...dda91f9d4886",
    "committed_at": "2017-05-24T11:17:27.000Z"
  },
  "jobs": [
    {
      "@type": "job",
      "@href": "/v3/job/235598630",
      "@representation": "minimal",
      "id": 235598630
    },
    {
      "@type": "job",
      "@href": "/v3/job/235598631",
      "@representation": "minimal",
      "id": 235598631
    },
    {
      "@type": "job",
      "@href": "/v3/job/235598632",
      "@representation": "minimal",
      "id": 235598632
    },
    {
      "@type": "job",
      "@href": "/v3/job/235598635",
      "@representation": "minimal",
      "id": 235598635
    },
    {
      "@type": "job",
      "@href": "/v3/job/235598641",
      "@representation": "minimal",
      "id": 235598641
    },
    {
      "@type": "job",
      "@href": "/v3/job/235598644",
      "@representation": "minimal",
      "id": 235598644
    },
    {
      "@type": "job",
      "@href": "/v3/job/235598647",
      "@representation": "minimal",
      "id": 235598647
    },
    {
      "@type": "job",
      "@href": "/v3/job/235598649",
      "@representation": "minimal",
      "id": 235598649
    },
    {
      "@type": "job",
      "@href": "/v3/job/235598650",
      "@representation": "minimal",
      "id": 235598650
    }
  ],
  "stages": [

  ],
  "created_by": {
    "@type": "user",
    "@href": "/v3/user/80410",
    "@representation": "minimal",
    "id": 80410,
    "login": "christophstrobl"
  },
  "updated_at": "2019-04-10T08:32:20.458Z"
}