{
  "@type": "build",
  "@href": "/v3/build/250306052",
  "@representation": "standard",
  "@permissions": {
    "read": true,
    "cancel": false,
    "restart": false
  },
  "id": 250306052,
  "number": "751",
  "state": "failed",
  "duration": 3133,
  "event_type": "push",
  "previous_state": "failed",
  "pull_request_title": null,
  "pull_request_number": null,
  "started_at": "2017-07-05T11:16:38.000Z",
  "finished_at": "2017-07-05T11:29:18.000Z",
  "private": false,
  "repository": {
    "@type": "repository",
    "@href": "/v3/repo/25241",
    "@representation": "minimal",
    "id": 25241,
    "name": "spring-data-mongodb",
    "slug": "spring-projects/spring-data-mongodb"
  },
  "branch": {
    "@type": "branch",
    "@href": "/v3/repo/25241/branch/1.10.x",
    "@representation": "minimal",
    "name": "1.10.x"
  },
  "tag": null,
  "commit": {
    "@type": "commit",
    "@representation": "minimal",
    "id": 72705023,
    "sha": "cbd9807f167e969c3236e38f7a3655d4405f3870",
    "ref": "refs/heads/1.10.x",
    "message": "DATAMONGO-1725 - Prevent NullPointerException in CloseableIterableCursorAdapter.close().",
    "compare_url": "https://github.com/spring-projects/spring-data-mongodb/compare/f672b17dfc40...cbd9807f167e",
    "committed_at": "2017-07-05T11:15:45.000Z"
  },
  "jobs": [
    {
      "@type": "job",
      "@href": "/v3/job/250306053",
      "@representation": "minimal",
      "id": 250306053
    },
    {
      "@type": "job",
      "@href": "/v3/job/250306054",
      "@representation": "minimal",
      "id": 250306054
    },
    {
      "@type": "job",
      "@href": "/v3/job/250306055",
      "@representation": "minimal",
      "id": 250306055
    },
    {
      "@type": "job",
      "@href": "/v3/job/250306056",
      "@representation": "minimal",
      "id": 250306056
    },
    {
      "@type": "job",
      "@href": "/v3/job/250306057",
      "@representation": "minimal",
      "id": 250306057
    },
    {
      "@type": "job",
      "@href": "/v3/job/250306058",
      "@representation": "minimal",
      "id": 250306058
    },
    {
      "@type": "job",
      "@href": "/v3/job/250306059",
      "@representation": "minimal",
      "id": 250306059
    },
    {
      "@type": "job",
      "@href": "/v3/job/250306060",
      "@representation": "minimal",
      "id": 250306060
    },
    {
      "@type": "job",
      "@href": "/v3/job/250306061",
      "@representation": "minimal",
      "id": 250306061
    }
  ],
  "stages": [

  ],
  "created_by": {
    "@type": "user",
    "@href": "/v3/user/65636",
    "@representation": "minimal",
    "id": 65636,
    "login": "odrotbohm"
  },
  "updated_at": "2019-04-10T08:32:20.458Z"
}