{
  "@type": "build",
  "@href": "/v3/build/253634640",
  "@representation": "standard",
  "@permissions": {
    "read": true,
    "cancel": false,
    "restart": false
  },
  "id": 253634640,
  "number": "24155",
  "state": "passed",
  "duration": 19987,
  "event_type": "pull_request",
  "previous_state": "failed",
  "pull_request_title": "Spill for join",
  "pull_request_number": 8166,
  "started_at": "2017-07-14T20:40:26.000Z",
  "finished_at": "2017-07-14T21:24:21.000Z",
  "private": false,
  "repository": {
    "@type": "repository",
    "@href": "/v3/repo/1504827",
    "@representation": "minimal",
    "id": 1504827,
    "name": "presto",
    "slug": "prestodb/presto"
  },
  "branch": {
    "@type": "branch",
    "@href": "/v3/repo/1504827/branch/master",
    "@representation": "minimal",
    "name": "master"
  },
  "tag": null,
  "commit": {
    "@type": "commit",
    "@representation": "minimal",
    "id": 73707439,
    "sha": "56b1192e7a606da5ef9fc6bfdccb07cf470772b8",
    "ref": "refs/pull/8166/merge",
    "message": "fixup! Add spill for join",
    "compare_url": "https://github.com/prestodb/presto/pull/8166",
    "committed_at": "2017-07-14T12:13:06.000Z"
  },
  "jobs": [
    {
      "@type": "job",
      "@href": "/v3/job/253634641",
      "@representation": "minimal",
      "id": 253634641
    },
    {
      "@type": "job",
      "@href": "/v3/job/253634642",
      "@representation": "minimal",
      "id": 253634642
    },
    {
      "@type": "job",
      "@href": "/v3/job/253634643",
      "@representation": "minimal",
      "id": 253634643
    },
    {
      "@type": "job",
      "@href": "/v3/job/253634644",
      "@representation": "minimal",
      "id": 253634644
    },
    {
      "@type": "job",
      "@href": "/v3/job/253634645",
      "@representation": "minimal",
      "id": 253634645
    },
    {
      "@type": "job",
      "@href": "/v3/job/253634646",
      "@representation": "minimal",
      "id": 253634646
    },
    {
      "@type": "job",
      "@href": "/v3/job/253634647",
      "@representation": "minimal",
      "id": 253634647
    },
    {
      "@type": "job",
      "@href": "/v3/job/253634648",
      "@representation": "minimal",
      "id": 253634648
    },
    {
      "@type": "job",
      "@href": "/v3/job/253634649",
      "@representation": "minimal",
      "id": 253634649
    },
    {
      "@type": "job",
      "@href": "/v3/job/253634650",
      "@representation": "minimal",
      "id": 253634650
    },
    {
      "@type": "job",
      "@href": "/v3/job/253634651",
      "@representation": "minimal",
      "id": 253634651
    }
  ],
  "stages": [

  ],
  "created_by": {
    "@type": "user",
    "@href": "/v3/user/446998",
    "@representation": "minimal",
    "id": 446998,
    "login": "findepi"
  },
  "updated_at": "2019-04-10T22:49:10.457Z"
}