{
  "@type": "build",
  "@href": "/v3/build/254359534",
  "@representation": "standard",
  "@permissions": {
    "read": true,
    "cancel": false,
    "restart": false
  },
  "id": 254359534,
  "number": "7121",
  "state": "failed",
  "duration": 1981,
  "event_type": "pull_request",
  "previous_state": "passed",
  "pull_request_title": "[GEOS-8223] Allow ordering layer contents in WMS using a \"sortBy\" vendor parameter, as well as mosaic contents in WCS",
  "pull_request_number": 2462,
  "started_at": "2017-07-26T14:10:04.000Z",
  "finished_at": "2017-07-26T14:43:05.000Z",
  "private": false,
  "repository": {
    "@type": "repository",
    "@href": "/v3/repo/365717",
    "@representation": "minimal",
    "id": 365717,
    "name": "geoserver",
    "slug": "geoserver/geoserver"
  },
  "branch": {
    "@type": "branch",
    "@href": "/v3/repo/365717/branch/master",
    "@representation": "minimal",
    "name": "master"
  },
  "tag": null,
  "commit": {
    "@type": "commit",
    "@representation": "minimal",
    "id": 73929219,
    "sha": "a9395a6726d9d9ee3b481fb7616f39e2411a6dbe",
    "ref": "refs/pull/2462/merge",
    "message": "Adding missing header",
    "compare_url": "https://github.com/geoserver/geoserver/pull/2462",
    "committed_at": "2017-07-17T08:57:45.000Z"
  },
  "jobs": [
    {
      "@type": "job",
      "@href": "/v3/job/254359535",
      "@representation": "minimal",
      "id": 254359535
    }
  ],
  "stages": [

  ],
  "created_by": {
    "@type": "user",
    "@href": "/v3/user/41556",
    "@representation": "minimal",
    "id": 41556,
    "login": "aaime"
  },
  "updated_at": "2019-04-10T12:06:36.132Z"
}