{
  "@type": "build",
  "@href": "/v3/build/288727423",
  "@representation": "standard",
  "@permissions": {
    "read": true,
    "cancel": false,
    "restart": false
  },
  "id": 288727423,
  "number": "550",
  "state": "failed",
  "duration": 246,
  "event_type": "pull_request",
  "previous_state": "passed",
  "pull_request_title": "WW-4871 Fixes StringConverter and improves it's tests",
  "pull_request_number": 173,
  "started_at": "2017-10-16T19:46:19Z",
  "finished_at": "2017-10-16T19:48:45Z",
  "private": false,
  "repository": {
    "@type": "repository",
    "@href": "/v3/repo/1769220",
    "@representation": "minimal",
    "id": 1769220,
    "name": "struts",
    "slug": "apache/struts"
  },
  "branch": {
    "@type": "branch",
    "@href": "/v3/repo/1769220/branch/master",
    "@representation": "minimal",
    "name": "master"
  },
  "tag": null,
  "commit": {
    "@type": "commit",
    "@representation": "minimal",
    "id": 84560013,
    "sha": "34becfbd8f5afae949b0ffd2593ec635bdbf6e30",
    "ref": "refs/pull/173/merge",
    "message": "WW-4871 Reverts setMinimumFractionDigits(1) to pass rest tests",
    "compare_url": "https://github.com/apache/struts/pull/173",
    "committed_at": "2017-10-16T19:45:26Z"
  },
  "jobs": [
    {
      "@type": "job",
      "@href": "/v3/job/288727425",
      "@representation": "minimal",
      "id": 288727425
    },
    {
      "@type": "job",
      "@href": "/v3/job/288727426",
      "@representation": "minimal",
      "id": 288727426
    }
  ],
  "stages": [

  ],
  "created_by": {
    "@type": "user",
    "@href": "/v3/user/560908",
    "@representation": "minimal",
    "id": 560908,
    "login": "yasserzamani"
  },
  "updated_at": "2019-04-11T01:16:52.160Z"
}