{
  "@type": "build",
  "@href": "/v3/build/325486956",
  "@representation": "standard",
  "@permissions": {
    "read": true,
    "cancel": false,
    "restart": false
  },
  "id": 325486956,
  "number": "1682",
  "state": "failed",
  "duration": 371,
  "event_type": "push",
  "previous_state": null,
  "pull_request_title": null,
  "pull_request_number": null,
  "started_at": "2018-01-05T15:34:43Z",
  "finished_at": "2018-01-05T15:38:20Z",
  "private": false,
  "repository": {
    "@type": "repository",
    "@href": "/v3/repo/7140",
    "@representation": "minimal",
    "id": 7140,
    "name": "metrics",
    "slug": "dropwizard/metrics"
  },
  "branch": {
    "@type": "branch",
    "@href": "/v3/repo/7140/branch/jp-readme-updates",
    "@representation": "minimal",
    "name": "jp-readme-updates"
  },
  "tag": null,
  "commit": {
    "@type": "commit",
    "@representation": "minimal",
    "id": 96680418,
    "sha": "0c328e5c89baea9cc9847610b4c0fb33b679b76c",
    "ref": "refs/heads/jp-readme-updates",
    "message": "Minor updates to the readme",
    "compare_url": "https://github.com/dropwizard/metrics/commit/0c328e5c89ba",
    "committed_at": "2018-01-05T15:34:07Z"
  },
  "jobs": [
    {
      "@type": "job",
      "@href": "/v3/job/325486958",
      "@representation": "minimal",
      "id": 325486958
    },
    {
      "@type": "job",
      "@href": "/v3/job/325486960",
      "@representation": "minimal",
      "id": 325486960
    }
  ],
  "stages": [

  ],
  "created_by": {
    "@type": "user",
    "@href": "/v3/user/38377",
    "@representation": "minimal",
    "id": 38377,
    "login": "jplock"
  },
  "updated_at": "2019-04-10T07:55:00.506Z"
}