{
  "@type": "build",
  "@href": "/v3/build/327014201",
  "@representation": "standard",
  "@permissions": {
    "read": true,
    "cancel": false,
    "restart": false
  },
  "id": 327014201,
  "number": "1714",
  "state": "failed",
  "duration": 341,
  "event_type": "push",
  "previous_state": "passed",
  "pull_request_title": null,
  "pull_request_number": null,
  "started_at": "2018-01-09T22:14:30Z",
  "finished_at": "2018-01-09T22:17:48Z",
  "private": false,
  "repository": {
    "@type": "repository",
    "@href": "/v3/repo/7140",
    "@representation": "minimal",
    "id": 7140,
    "name": "metrics",
    "slug": "dropwizard/metrics"
  },
  "branch": {
    "@type": "branch",
    "@href": "/v3/repo/7140/branch/5.0-development",
    "@representation": "minimal",
    "name": "5.0-development"
  },
  "tag": null,
  "commit": {
    "@type": "commit",
    "@representation": "minimal",
    "id": 97137251,
    "sha": "c7e180ff789ea8c24e0064f8187496a396f16044",
    "ref": "refs/heads/5.0-development",
    "message": "Move to the io.dropwizard.metrics5 package (#1255)\n\nThe new package name allows to distinguish between the non-compatible\r\nAPIs of Metrics 3/4 and Metrics 5 and prevent API conflict when someone\r\nby mistake have different version of Metrics in the classpath.",
    "compare_url": "https://github.com/dropwizard/metrics/compare/0cf7d087f785...c7e180ff789e",
    "committed_at": "2018-01-09T22:13:48Z"
  },
  "jobs": [
    {
      "@type": "job",
      "@href": "/v3/job/327014202",
      "@representation": "minimal",
      "id": 327014202
    },
    {
      "@type": "job",
      "@href": "/v3/job/327014203",
      "@representation": "minimal",
      "id": 327014203
    }
  ],
  "stages": [

  ],
  "created_by": {
    "@type": "user",
    "@href": "/v3/user/89093",
    "@representation": "minimal",
    "id": 89093,
    "login": "arteam"
  },
  "updated_at": "2019-04-10T07:55:00.506Z"
}