{
  "@type": "build",
  "@href": "/v3/build/335129428",
  "@representation": "standard",
  "@permissions": {
    "read": true,
    "cancel": false,
    "restart": false
  },
  "id": 335129428,
  "number": "6946",
  "state": "failed",
  "duration": 336,
  "event_type": "push",
  "previous_state": "failed",
  "pull_request_title": null,
  "pull_request_number": null,
  "started_at": "2018-01-30T12:28:02.000Z",
  "finished_at": "2018-01-30T12:33:38.000Z",
  "private": false,
  "repository": {
    "@type": "repository",
    "@href": "/v3/repo/5547194",
    "@representation": "minimal",
    "id": 5547194,
    "name": "matsim",
    "slug": "matsim-org/matsim"
  },
  "branch": {
    "@type": "branch",
    "@href": "/v3/repo/5547194/branch/connection-scan",
    "@representation": "minimal",
    "name": "connection-scan"
  },
  "tag": null,
  "commit": {
    "@type": "commit",
    "@representation": "minimal",
    "id": 99615029,
    "sha": "ca9d801b74333c8d428559b9ab3c7b6dfc56e14a",
    "ref": "refs/heads/connection-scan",
    "message": "fix heap space bug",
    "compare_url": "https://github.com/matsim-org/matsim/compare/918b616998b1...ca9d801b7433",
    "committed_at": "2018-01-30T12:27:31.000Z"
  },
  "jobs": [
    {
      "@type": "job",
      "@href": "/v3/job/335129430",
      "@representation": "minimal",
      "id": 335129430
    },
    {
      "@type": "job",
      "@href": "/v3/job/335129432",
      "@representation": "minimal",
      "id": 335129432
    },
    {
      "@type": "job",
      "@href": "/v3/job/335129435",
      "@representation": "minimal",
      "id": 335129435
    },
    {
      "@type": "job",
      "@href": "/v3/job/335129436",
      "@representation": "minimal",
      "id": 335129436
    },
    {
      "@type": "job",
      "@href": "/v3/job/335129437",
      "@representation": "minimal",
      "id": 335129437
    },
    {
      "@type": "job",
      "@href": "/v3/job/335129440",
      "@representation": "minimal",
      "id": 335129440
    },
    {
      "@type": "job",
      "@href": "/v3/job/335129441",
      "@representation": "minimal",
      "id": 335129441
    },
    {
      "@type": "job",
      "@href": "/v3/job/335129442",
      "@representation": "minimal",
      "id": 335129442
    },
    {
      "@type": "job",
      "@href": "/v3/job/335129443",
      "@representation": "minimal",
      "id": 335129443
    },
    {
      "@type": "job",
      "@href": "/v3/job/335129444",
      "@representation": "minimal",
      "id": 335129444
    },
    {
      "@type": "job",
      "@href": "/v3/job/335129445",
      "@representation": "minimal",
      "id": 335129445
    },
    {
      "@type": "job",
      "@href": "/v3/job/335129446",
      "@representation": "minimal",
      "id": 335129446
    },
    {
      "@type": "job",
      "@href": "/v3/job/335129447",
      "@representation": "minimal",
      "id": 335129447
    },
    {
      "@type": "job",
      "@href": "/v3/job/335129448",
      "@representation": "minimal",
      "id": 335129448
    },
    {
      "@type": "job",
      "@href": "/v3/job/335129449",
      "@representation": "minimal",
      "id": 335129449
    },
    {
      "@type": "job",
      "@href": "/v3/job/335129450",
      "@representation": "minimal",
      "id": 335129450
    },
    {
      "@type": "job",
      "@href": "/v3/job/335129451",
      "@representation": "minimal",
      "id": 335129451
    },
    {
      "@type": "job",
      "@href": "/v3/job/335129452",
      "@representation": "minimal",
      "id": 335129452
    },
    {
      "@type": "job",
      "@href": "/v3/job/335129453",
      "@representation": "minimal",
      "id": 335129453
    },
    {
      "@type": "job",
      "@href": "/v3/job/335129454",
      "@representation": "minimal",
      "id": 335129454
    },
    {
      "@type": "job",
      "@href": "/v3/job/335129455",
      "@representation": "minimal",
      "id": 335129455
    },
    {
      "@type": "job",
      "@href": "/v3/job/335129456",
      "@representation": "minimal",
      "id": 335129456
    },
    {
      "@type": "job",
      "@href": "/v3/job/335129457",
      "@representation": "minimal",
      "id": 335129457
    },
    {
      "@type": "job",
      "@href": "/v3/job/335129458",
      "@representation": "minimal",
      "id": 335129458
    },
    {
      "@type": "job",
      "@href": "/v3/job/335129459",
      "@representation": "minimal",
      "id": 335129459
    },
    {
      "@type": "job",
      "@href": "/v3/job/335129460",
      "@representation": "minimal",
      "id": 335129460
    },
    {
      "@type": "job",
      "@href": "/v3/job/335129461",
      "@representation": "minimal",
      "id": 335129461
    },
    {
      "@type": "job",
      "@href": "/v3/job/335129462",
      "@representation": "minimal",
      "id": 335129462
    },
    {
      "@type": "job",
      "@href": "/v3/job/335129463",
      "@representation": "minimal",
      "id": 335129463
    },
    {
      "@type": "job",
      "@href": "/v3/job/335129464",
      "@representation": "minimal",
      "id": 335129464
    },
    {
      "@type": "job",
      "@href": "/v3/job/335129465",
      "@representation": "minimal",
      "id": 335129465
    },
    {
      "@type": "job",
      "@href": "/v3/job/335129466",
      "@representation": "minimal",
      "id": 335129466
    },
    {
      "@type": "job",
      "@href": "/v3/job/335129467",
      "@representation": "minimal",
      "id": 335129467
    },
    {
      "@type": "job",
      "@href": "/v3/job/335129468",
      "@representation": "minimal",
      "id": 335129468
    },
    {
      "@type": "job",
      "@href": "/v3/job/335129469",
      "@representation": "minimal",
      "id": 335129469
    },
    {
      "@type": "job",
      "@href": "/v3/job/335129470",
      "@representation": "minimal",
      "id": 335129470
    },
    {
      "@type": "job",
      "@href": "/v3/job/335129471",
      "@representation": "minimal",
      "id": 335129471
    }
  ],
  "stages": [
    {
      "@type": "stage",
      "@representation": "minimal",
      "id": 1148197,
      "number": 2,
      "name": "Test",
      "state": "canceled",
      "started_at": null,
      "finished_at": "2018-01-30T12:33:38Z"
    },
    {
      "@type": "stage",
      "@representation": "minimal",
      "id": 1148196,
      "number": 1,
      "name": "Package",
      "state": "failed",
      "started_at": "2018-01-30T12:28:02Z",
      "finished_at": "2018-01-30T12:33:38Z"
    }
  ],
  "created_by": {
    "@type": "user",
    "@href": "/v3/user/274637",
    "@representation": "minimal",
    "id": 274637,
    "login": "gabrielthunig"
  },
  "updated_at": "2019-04-12T05:22:32.561Z"
}