{
  "@type": "build",
  "@href": "/v3/build/339178482",
  "@representation": "standard",
  "@permissions": {
    "read": true,
    "cancel": false,
    "restart": false
  },
  "id": 339178482,
  "number": "2076",
  "state": "failed",
  "duration": 6685,
  "event_type": "push",
  "previous_state": "failed",
  "pull_request_title": null,
  "pull_request_number": null,
  "started_at": "2018-02-08T21:06:43Z",
  "finished_at": "2018-02-08T21:41:37Z",
  "private": false,
  "repository": {
    "@type": "repository",
    "@href": "/v3/repo/3834778",
    "@representation": "minimal",
    "id": 3834778,
    "name": "keycloak",
    "slug": "stianst/keycloak"
  },
  "branch": {
    "@type": "branch",
    "@href": "/v3/repo/3834778/branch/KEYCLOAK-6519",
    "@representation": "minimal",
    "name": "KEYCLOAK-6519"
  },
  "tag": null,
  "commit": {
    "@type": "commit",
    "@representation": "minimal",
    "id": 100842736,
    "sha": "582abedadff0734441a16725d3fe1c809bcf4e1c",
    "ref": "refs/heads/KEYCLOAK-6519",
    "message": "KEYCLOAK-6519 Theme resource provider",
    "compare_url": "https://github.com/stianst/keycloak/compare/6589654bf2f4...582abedadff0",
    "committed_at": "2018-02-08T21:06:02Z"
  },
  "jobs": [
    {
      "@type": "job",
      "@href": "/v3/job/339178483",
      "@representation": "minimal",
      "id": 339178483
    },
    {
      "@type": "job",
      "@href": "/v3/job/339178484",
      "@representation": "minimal",
      "id": 339178484
    },
    {
      "@type": "job",
      "@href": "/v3/job/339178485",
      "@representation": "minimal",
      "id": 339178485
    },
    {
      "@type": "job",
      "@href": "/v3/job/339178486",
      "@representation": "minimal",
      "id": 339178486
    },
    {
      "@type": "job",
      "@href": "/v3/job/339178487",
      "@representation": "minimal",
      "id": 339178487
    },
    {
      "@type": "job",
      "@href": "/v3/job/339178488",
      "@representation": "minimal",
      "id": 339178488
    },
    {
      "@type": "job",
      "@href": "/v3/job/339178489",
      "@representation": "minimal",
      "id": 339178489
    }
  ],
  "stages": [

  ],
  "created_by": {
    "@type": "user",
    "@href": "/v3/user/120597",
    "@representation": "minimal",
    "id": 120597,
    "login": "stianst"
  },
  "updated_at": "2019-04-11T17:44:31.373Z"
}