{
  "@type": "build",
  "@href": "/v3/build/339476684",
  "@representation": "standard",
  "@permissions": {
    "read": true,
    "cancel": false,
    "restart": false
  },
  "id": 339476684,
  "number": "7077",
  "state": "failed",
  "duration": 290,
  "event_type": "push",
  "previous_state": "failed",
  "pull_request_title": null,
  "pull_request_number": null,
  "started_at": "2018-02-09T14:25:14.000Z",
  "finished_at": "2018-02-09T14:30:04.000Z",
  "private": false,
  "repository": {
    "@type": "repository",
    "@href": "/v3/repo/5547194",
    "@representation": "minimal",
    "id": 5547194,
    "name": "matsim",
    "slug": "matsim-org/matsim"
  },
  "branch": {
    "@type": "branch",
    "@href": "/v3/repo/5547194/branch/bicycleScoring",
    "@representation": "minimal",
    "name": "bicycleScoring"
  },
  "tag": null,
  "commit": {
    "@type": "commit",
    "@representation": "minimal",
    "id": 100934191,
    "sha": "aa54e9a2624df39101ec8d28adfd4a0c1abd74b5",
    "ref": "refs/heads/bicycleScoring",
    "message": "update tests",
    "compare_url": "https://github.com/matsim-org/matsim/compare/12e95ca21d4c...aa54e9a2624d",
    "committed_at": "2018-02-09T14:24:10.000Z"
  },
  "jobs": [
    {
      "@type": "job",
      "@href": "/v3/job/339476685",
      "@representation": "minimal",
      "id": 339476685
    },
    {
      "@type": "job",
      "@href": "/v3/job/339476686",
      "@representation": "minimal",
      "id": 339476686
    },
    {
      "@type": "job",
      "@href": "/v3/job/339476687",
      "@representation": "minimal",
      "id": 339476687
    },
    {
      "@type": "job",
      "@href": "/v3/job/339476688",
      "@representation": "minimal",
      "id": 339476688
    },
    {
      "@type": "job",
      "@href": "/v3/job/339476689",
      "@representation": "minimal",
      "id": 339476689
    },
    {
      "@type": "job",
      "@href": "/v3/job/339476690",
      "@representation": "minimal",
      "id": 339476690
    },
    {
      "@type": "job",
      "@href": "/v3/job/339476691",
      "@representation": "minimal",
      "id": 339476691
    },
    {
      "@type": "job",
      "@href": "/v3/job/339476692",
      "@representation": "minimal",
      "id": 339476692
    },
    {
      "@type": "job",
      "@href": "/v3/job/339476693",
      "@representation": "minimal",
      "id": 339476693
    },
    {
      "@type": "job",
      "@href": "/v3/job/339476694",
      "@representation": "minimal",
      "id": 339476694
    },
    {
      "@type": "job",
      "@href": "/v3/job/339476695",
      "@representation": "minimal",
      "id": 339476695
    },
    {
      "@type": "job",
      "@href": "/v3/job/339476696",
      "@representation": "minimal",
      "id": 339476696
    },
    {
      "@type": "job",
      "@href": "/v3/job/339476697",
      "@representation": "minimal",
      "id": 339476697
    },
    {
      "@type": "job",
      "@href": "/v3/job/339476698",
      "@representation": "minimal",
      "id": 339476698
    },
    {
      "@type": "job",
      "@href": "/v3/job/339476699",
      "@representation": "minimal",
      "id": 339476699
    },
    {
      "@type": "job",
      "@href": "/v3/job/339476700",
      "@representation": "minimal",
      "id": 339476700
    },
    {
      "@type": "job",
      "@href": "/v3/job/339476701",
      "@representation": "minimal",
      "id": 339476701
    },
    {
      "@type": "job",
      "@href": "/v3/job/339476702",
      "@representation": "minimal",
      "id": 339476702
    },
    {
      "@type": "job",
      "@href": "/v3/job/339476703",
      "@representation": "minimal",
      "id": 339476703
    },
    {
      "@type": "job",
      "@href": "/v3/job/339476704",
      "@representation": "minimal",
      "id": 339476704
    },
    {
      "@type": "job",
      "@href": "/v3/job/339476705",
      "@representation": "minimal",
      "id": 339476705
    },
    {
      "@type": "job",
      "@href": "/v3/job/339476706",
      "@representation": "minimal",
      "id": 339476706
    },
    {
      "@type": "job",
      "@href": "/v3/job/339476707",
      "@representation": "minimal",
      "id": 339476707
    },
    {
      "@type": "job",
      "@href": "/v3/job/339476708",
      "@representation": "minimal",
      "id": 339476708
    },
    {
      "@type": "job",
      "@href": "/v3/job/339476709",
      "@representation": "minimal",
      "id": 339476709
    },
    {
      "@type": "job",
      "@href": "/v3/job/339476710",
      "@representation": "minimal",
      "id": 339476710
    },
    {
      "@type": "job",
      "@href": "/v3/job/339476711",
      "@representation": "minimal",
      "id": 339476711
    },
    {
      "@type": "job",
      "@href": "/v3/job/339476712",
      "@representation": "minimal",
      "id": 339476712
    },
    {
      "@type": "job",
      "@href": "/v3/job/339476713",
      "@representation": "minimal",
      "id": 339476713
    },
    {
      "@type": "job",
      "@href": "/v3/job/339476714",
      "@representation": "minimal",
      "id": 339476714
    },
    {
      "@type": "job",
      "@href": "/v3/job/339476715",
      "@representation": "minimal",
      "id": 339476715
    },
    {
      "@type": "job",
      "@href": "/v3/job/339476716",
      "@representation": "minimal",
      "id": 339476716
    },
    {
      "@type": "job",
      "@href": "/v3/job/339476717",
      "@representation": "minimal",
      "id": 339476717
    },
    {
      "@type": "job",
      "@href": "/v3/job/339476718",
      "@representation": "minimal",
      "id": 339476718
    },
    {
      "@type": "job",
      "@href": "/v3/job/339476719",
      "@representation": "minimal",
      "id": 339476719
    },
    {
      "@type": "job",
      "@href": "/v3/job/339476720",
      "@representation": "minimal",
      "id": 339476720
    },
    {
      "@type": "job",
      "@href": "/v3/job/339476721",
      "@representation": "minimal",
      "id": 339476721
    }
  ],
  "stages": [
    {
      "@type": "stage",
      "@representation": "minimal",
      "id": 1229463,
      "number": 2,
      "name": "Test",
      "state": "canceled",
      "started_at": null,
      "finished_at": "2018-02-09T14:30:04Z"
    },
    {
      "@type": "stage",
      "@representation": "minimal",
      "id": 1229462,
      "number": 1,
      "name": "Package",
      "state": "failed",
      "started_at": "2018-02-09T14:25:14Z",
      "finished_at": "2018-02-09T14:30:04Z"
    }
  ],
  "created_by": {
    "@type": "user",
    "@href": "/v3/user/286343",
    "@representation": "minimal",
    "id": 286343,
    "login": "dziemke"
  },
  "updated_at": "2019-04-12T05:22:32.561Z"
}