{
  "@type": "build",
  "@href": "/v3/build/349675737",
  "@representation": "standard",
  "@permissions": {
    "read": true,
    "cancel": false,
    "restart": false
  },
  "id": 349675737,
  "number": "1389",
  "state": "failed",
  "duration": 141,
  "event_type": "push",
  "previous_state": null,
  "pull_request_title": null,
  "pull_request_number": null,
  "started_at": "2018-03-06T06:47:37.000Z",
  "finished_at": "2018-03-06T06:49:58.000Z",
  "private": false,
  "repository": {
    "@type": "repository",
    "@href": "/v3/repo/10730620",
    "@representation": "minimal",
    "id": 10730620,
    "name": "konig",
    "slug": "konigio/konig"
  },
  "branch": {
    "@type": "branch",
    "@href": "/v3/repo/10730620/branch/DamodarAllareddy%2F%23755",
    "@representation": "minimal",
    "name": "DamodarAllareddy/#755"
  },
  "tag": null,
  "commit": {
    "@type": "commit",
    "@representation": "minimal",
    "id": 104063551,
    "sha": "c280d284d20f22b1185da02964ff69b8a7c2362f",
    "ref": "refs/heads/DamodarAllareddy/#755",
    "message": "closes #755",
    "compare_url": "https://github.com/konigio/konig/commit/c280d284d20f",
    "committed_at": "2018-03-06T06:46:45.000Z"
  },
  "jobs": [
    {
      "@type": "job",
      "@href": "/v3/job/349675738",
      "@representation": "minimal",
      "id": 349675738
    }
  ],
  "stages": [

  ],
  "created_by": {
    "@type": "user",
    "@href": "/v3/user/1148362",
    "@representation": "minimal",
    "id": 1148362,
    "login": "DamodarAllareddy"
  },
  "updated_at": "2019-04-13T16:59:08.724Z"
}