{
  "@type": "build",
  "@href": "/v3/build/365964614",
  "@representation": "standard",
  "@permissions": {
    "read": true,
    "cancel": false,
    "restart": false
  },
  "id": 365964614,
  "number": "1820",
  "state": "failed",
  "duration": 648,
  "event_type": "push",
  "previous_state": null,
  "pull_request_title": null,
  "pull_request_number": null,
  "started_at": "2018-04-13T06:27:35Z",
  "finished_at": "2018-04-13T06:38:23Z",
  "private": false,
  "repository": {
    "@type": "repository",
    "@href": "/v3/repo/2006926",
    "@representation": "minimal",
    "id": 2006926,
    "name": "terasoluna-tourreservation",
    "slug": "terasolunaorg/terasoluna-tourreservation"
  },
  "branch": {
    "@type": "branch",
    "@href": "/v3/repo/2006926/branch/issue%2F541_fix_travis_5.2.x_test",
    "@representation": "minimal",
    "name": "issue/541_fix_travis_5.2.x_test"
  },
  "tag": null,
  "commit": {
    "@type": "commit",
    "@representation": "minimal",
    "id": 109209792,
    "sha": "fb6c7395a8afd9285de46dc36ace9c142511028d",
    "ref": "refs/heads/issue/541_fix_travis_5.2.x_test",
    "message": "Merge pull request #529 from terasolunaorg/issues/522_add_firefox_setting_5.2.x\n\n[5.2.x] add firefox preference setting of no proxy. #522",
    "compare_url": "https://github.com/terasolunaorg/terasoluna-tourreservation/compare/issue/541_fix_travis_5.2.x_test",
    "committed_at": null
  },
  "jobs": [
    {
      "@type": "job",
      "@href": "/v3/job/365964615",
      "@representation": "minimal",
      "id": 365964615
    }
  ],
  "stages": [

  ],
  "created_by": {
    "@type": "user",
    "@href": "/v3/user/1167969",
    "@representation": "minimal",
    "id": 1167969,
    "login": "btmorikawanoh"
  },
  "updated_at": "2019-04-11T03:35:24.237Z"
}