{
  "@type": "build",
  "@href": "/v3/build/372794283",
  "@representation": "standard",
  "@permissions": {
    "read": true,
    "cancel": false,
    "restart": false
  },
  "id": 372794283,
  "number": "15564",
  "state": "failed",
  "duration": 7051,
  "event_type": "pull_request",
  "previous_state": "failed",
  "pull_request_title": "Make lookup offheap buffer configurable",
  "pull_request_number": 5696,
  "started_at": "2018-04-29T21:05:44Z",
  "finished_at": "2018-04-29T22:03:10Z",
  "private": false,
  "repository": {
    "@type": "repository",
    "@href": "/v3/repo/578446",
    "@representation": "minimal",
    "id": 578446,
    "name": "incubator-druid",
    "slug": "apache/incubator-druid"
  },
  "branch": {
    "@type": "branch",
    "@href": "/v3/repo/578446/branch/master",
    "@representation": "minimal",
    "name": "master"
  },
  "tag": null,
  "commit": {
    "@type": "commit",
    "@representation": "minimal",
    "id": 111382888,
    "sha": "2ad259523d33e3df9b9e6aba7346b599364d1280",
    "ref": "refs/pull/5696/merge",
    "message": "Update docs",
    "compare_url": "https://github.com/druid-io/druid/pull/5696",
    "committed_at": "2018-04-29T21:05:07Z"
  },
  "jobs": [
    {
      "@type": "job",
      "@href": "/v3/job/372794285",
      "@representation": "minimal",
      "id": 372794285
    },
    {
      "@type": "job",
      "@href": "/v3/job/372794286",
      "@representation": "minimal",
      "id": 372794286
    },
    {
      "@type": "job",
      "@href": "/v3/job/372794287",
      "@representation": "minimal",
      "id": 372794287
    },
    {
      "@type": "job",
      "@href": "/v3/job/372794288",
      "@representation": "minimal",
      "id": 372794288
    },
    {
      "@type": "job",
      "@href": "/v3/job/372794289",
      "@representation": "minimal",
      "id": 372794289
    }
  ],
  "stages": [

  ],
  "created_by": {
    "@type": "user",
    "@href": "/v3/user/268406",
    "@representation": "minimal",
    "id": 268406,
    "login": "Dylan1312"
  },
  "updated_at": "2019-04-10T14:44:12.453Z"
}