{
  "@type": "build",
  "@href": "/v3/build/372924705",
  "@representation": "standard",
  "@permissions": {
    "read": true,
    "cancel": false,
    "restart": false
  },
  "id": 372924705,
  "number": "15572",
  "state": "passed",
  "duration": 5809,
  "event_type": "pull_request",
  "previous_state": "failed",
  "pull_request_title": "[Backport] Use unique segment paths for Kafka indexing (#5692)",
  "pull_request_number": 5718,
  "started_at": "2018-04-30T09:25:45.000Z",
  "finished_at": "2018-04-30T09:47:20.000Z",
  "private": false,
  "repository": {
    "@type": "repository",
    "@href": "/v3/repo/578446",
    "@representation": "minimal",
    "id": 578446,
    "name": "incubator-druid",
    "slug": "apache/incubator-druid"
  },
  "branch": {
    "@type": "branch",
    "@href": "/v3/repo/578446/branch/0.12.1",
    "@representation": "minimal",
    "name": "0.12.1"
  },
  "tag": null,
  "commit": {
    "@type": "commit",
    "@representation": "minimal",
    "id": 111425747,
    "sha": "a8737642f17696700b75f4aa8af203ed6751fd3c",
    "ref": "refs/pull/5718/merge",
    "message": "Use unique segment paths for Kafka indexing (#5692)\n\n* support unique segment file paths\n\n* forbiddenapis\n\n* code review changes\n\n* code review changes\n\n* code review changes\n\n* checkstyle fix",
    "compare_url": "https://github.com/druid-io/druid/pull/5718",
    "committed_at": "2018-04-30T08:01:01.000Z"
  },
  "jobs": [
    {
      "@type": "job",
      "@href": "/v3/job/372924706",
      "@representation": "minimal",
      "id": 372924706
    },
    {
      "@type": "job",
      "@href": "/v3/job/372924707",
      "@representation": "minimal",
      "id": 372924707
    },
    {
      "@type": "job",
      "@href": "/v3/job/372924708",
      "@representation": "minimal",
      "id": 372924708
    },
    {
      "@type": "job",
      "@href": "/v3/job/372924709",
      "@representation": "minimal",
      "id": 372924709
    },
    {
      "@type": "job",
      "@href": "/v3/job/372924710",
      "@representation": "minimal",
      "id": 372924710
    }
  ],
  "stages": [

  ],
  "created_by": {
    "@type": "user",
    "@href": "/v3/user/562468",
    "@representation": "minimal",
    "id": 562468,
    "login": "dclim"
  },
  "updated_at": "2019-04-10T14:44:12.453Z"
}