{
  "@type": "build",
  "@href": "/v3/build/382903835",
  "@representation": "standard",
  "@permissions": {
    "read": true,
    "cancel": false,
    "restart": false
  },
  "id": 382903835,
  "number": "3607",
  "state": "failed",
  "duration": 23311,
  "event_type": "push",
  "previous_state": "canceled",
  "pull_request_title": null,
  "pull_request_number": null,
  "started_at": "2018-05-23T21:54:01.000Z",
  "finished_at": "2018-05-23T23:23:12.000Z",
  "private": false,
  "repository": {
    "@type": "repository",
    "@href": "/v3/repo/3173988",
    "@representation": "minimal",
    "id": 3173988,
    "name": "flink",
    "slug": "tillrohrmann/flink"
  },
  "branch": {
    "@type": "branch",
    "@href": "/v3/repo/3173988/branch/fixTaskExecutorRegistration",
    "@representation": "minimal",
    "name": "fixTaskExecutorRegistration"
  },
  "tag": null,
  "commit": {
    "@type": "commit",
    "@representation": "minimal",
    "id": 114553087,
    "sha": "c1e82fd7de901f9b0dd29f2cfb6fa170079cf101",
    "ref": "refs/heads/fixTaskExecutorRegistration",
    "message": "fixup! fixup! [FLINK-9427] Fix registration and request slot race condition in TaskExecutor",
    "compare_url": "https://github.com/tillrohrmann/flink/compare/88596be05085...c1e82fd7de90",
    "committed_at": "2018-05-23T21:52:43.000Z"
  },
  "jobs": [
    {
      "@type": "job",
      "@href": "/v3/job/382903836",
      "@representation": "minimal",
      "id": 382903836
    },
    {
      "@type": "job",
      "@href": "/v3/job/382903837",
      "@representation": "minimal",
      "id": 382903837
    },
    {
      "@type": "job",
      "@href": "/v3/job/382903838",
      "@representation": "minimal",
      "id": 382903838
    },
    {
      "@type": "job",
      "@href": "/v3/job/382903839",
      "@representation": "minimal",
      "id": 382903839
    },
    {
      "@type": "job",
      "@href": "/v3/job/382903840",
      "@representation": "minimal",
      "id": 382903840
    },
    {
      "@type": "job",
      "@href": "/v3/job/382903841",
      "@representation": "minimal",
      "id": 382903841
    },
    {
      "@type": "job",
      "@href": "/v3/job/382903842",
      "@representation": "minimal",
      "id": 382903842
    },
    {
      "@type": "job",
      "@href": "/v3/job/382903843",
      "@representation": "minimal",
      "id": 382903843
    },
    {
      "@type": "job",
      "@href": "/v3/job/382903844",
      "@representation": "minimal",
      "id": 382903844
    },
    {
      "@type": "job",
      "@href": "/v3/job/382903845",
      "@representation": "minimal",
      "id": 382903845
    }
  ],
  "stages": [

  ],
  "created_by": {
    "@type": "user",
    "@href": "/v3/user/101466",
    "@representation": "minimal",
    "id": 101466,
    "login": "tillrohrmann"
  },
  "updated_at": "2019-04-11T13:31:03.950Z"
}