{
  "@type": "build",
  "@href": "/v3/build/388836284",
  "@representation": "standard",
  "@permissions": {
    "read": true,
    "cancel": false,
    "restart": false
  },
  "id": 388836284,
  "number": "5401",
  "state": "failed",
  "duration": 1796,
  "event_type": "pull_request",
  "previous_state": "passed",
  "pull_request_title": "Review: refactor: move SpoonMetaModel from src/test to src/main",
  "pull_request_number": 2016,
  "started_at": "2018-06-06T15:49:32Z",
  "finished_at": "2018-06-06T15:58:18Z",
  "private": false,
  "repository": {
    "@type": "repository",
    "@href": "/v3/repo/2800492",
    "@representation": "minimal",
    "id": 2800492,
    "name": "spoon",
    "slug": "INRIA/spoon"
  },
  "branch": {
    "@type": "branch",
    "@href": "/v3/repo/2800492/branch/master",
    "@representation": "minimal",
    "name": "master"
  },
  "tag": null,
  "commit": {
    "@type": "commit",
    "@representation": "minimal",
    "id": 116466820,
    "sha": "af943f67ddf6947ebdbcccb99d1dc25a67022135",
    "ref": "refs/pull/2016/merge",
    "message": "up",
    "compare_url": "https://github.com/INRIA/spoon/pull/2016",
    "committed_at": "2018-06-06T15:48:43Z"
  },
  "jobs": [
    {
      "@type": "job",
      "@href": "/v3/job/388836285",
      "@representation": "minimal",
      "id": 388836285
    },
    {
      "@type": "job",
      "@href": "/v3/job/388836286",
      "@representation": "minimal",
      "id": 388836286
    },
    {
      "@type": "job",
      "@href": "/v3/job/388836287",
      "@representation": "minimal",
      "id": 388836287
    },
    {
      "@type": "job",
      "@href": "/v3/job/388836288",
      "@representation": "minimal",
      "id": 388836288
    },
    {
      "@type": "job",
      "@href": "/v3/job/388836289",
      "@representation": "minimal",
      "id": 388836289
    },
    {
      "@type": "job",
      "@href": "/v3/job/388836290",
      "@representation": "minimal",
      "id": 388836290
    }
  ],
  "stages": [

  ],
  "created_by": {
    "@type": "user",
    "@href": "/v3/user/90405",
    "@representation": "minimal",
    "id": 90405,
    "login": "monperrus"
  },
  "updated_at": "2019-04-11T10:57:16.861Z"
}