{
  "@type": "build",
  "@href": "/v3/build/395886149",
  "@representation": "standard",
  "@permissions": {
    "read": true,
    "cancel": false,
    "restart": false
  },
  "id": 395886149,
  "number": "421",
  "state": "failed",
  "duration": 1485,
  "event_type": "pull_request",
  "previous_state": "errored",
  "pull_request_title": "[WIP] add hystrix integration extension",
  "pull_request_number": 195,
  "started_at": "2018-06-23T17:42:45.000Z",
  "finished_at": "2018-06-23T17:51:44.000Z",
  "private": false,
  "repository": {
    "@type": "repository",
    "@href": "/v3/repo/18588815",
    "@representation": "minimal",
    "id": 18588815,
    "name": "sofa-rpc",
    "slug": "alipay/sofa-rpc"
  },
  "branch": {
    "@type": "branch",
    "@href": "/v3/repo/18588815/branch/master",
    "@representation": "minimal",
    "name": "master"
  },
  "tag": null,
  "commit": {
    "@type": "commit",
    "@representation": "minimal",
    "id": 118717106,
    "sha": "1639ba8d2cf5b9b65197d302c3f6bdf499468de5",
    "ref": "refs/pull/195/merge",
    "message": "add hystrix integration extension",
    "compare_url": "https://github.com/alipay/sofa-rpc/pull/195",
    "committed_at": "2018-06-23T17:27:26.000Z"
  },
  "jobs": [
    {
      "@type": "job",
      "@href": "/v3/job/395886150",
      "@representation": "minimal",
      "id": 395886150
    },
    {
      "@type": "job",
      "@href": "/v3/job/395886151",
      "@representation": "minimal",
      "id": 395886151
    },
    {
      "@type": "job",
      "@href": "/v3/job/395886152",
      "@representation": "minimal",
      "id": 395886152
    }
  ],
  "stages": [

  ],
  "created_by": {
    "@type": "user",
    "@href": "/v3/user/713008",
    "@representation": "minimal",
    "id": 713008,
    "login": "ScienJus"
  },
  "updated_at": "2019-04-15T01:40:17.336Z"
}