{
  "@type": "build",
  "@href": "/v3/build/410304455",
  "@representation": "standard",
  "@permissions": {
    "read": true,
    "cancel": false,
    "restart": false
  },
  "id": 410304455,
  "number": "26395",
  "state": "failed",
  "duration": 23472,
  "event_type": "push",
  "previous_state": "passed",
  "pull_request_title": null,
  "pull_request_number": null,
  "started_at": "2018-07-31T14:14:17Z",
  "finished_at": "2018-07-31T15:31:41Z",
  "private": false,
  "repository": {
    "@type": "repository",
    "@href": "/v3/repo/2476141",
    "@representation": "minimal",
    "id": 2476141,
    "name": "flink",
    "slug": "apache/flink"
  },
  "branch": {
    "@type": "branch",
    "@href": "/v3/repo/2476141/branch/release-1.5",
    "@representation": "minimal",
    "name": "release-1.5"
  },
  "tag": null,
  "commit": {
    "@type": "commit",
    "@representation": "minimal",
    "id": 123201086,
    "sha": "d44cb153fc076bb3af44602fba1268b5bca4e621",
    "ref": "refs/heads/release-1.5",
    "message": "[FLINK-9978][release] Include relative path in source release sha file\n\nThis closes #6436.",
    "compare_url": "https://github.com/apache/flink/compare/9f1f0a87bdde...d44cb153fc07",
    "committed_at": "2018-07-31T12:41:33Z"
  },
  "jobs": [
    {
      "@type": "job",
      "@href": "/v3/job/410304456",
      "@representation": "minimal",
      "id": 410304456
    },
    {
      "@type": "job",
      "@href": "/v3/job/410304457",
      "@representation": "minimal",
      "id": 410304457
    },
    {
      "@type": "job",
      "@href": "/v3/job/410304458",
      "@representation": "minimal",
      "id": 410304458
    },
    {
      "@type": "job",
      "@href": "/v3/job/410304460",
      "@representation": "minimal",
      "id": 410304460
    },
    {
      "@type": "job",
      "@href": "/v3/job/410304461",
      "@representation": "minimal",
      "id": 410304461
    },
    {
      "@type": "job",
      "@href": "/v3/job/410304462",
      "@representation": "minimal",
      "id": 410304462
    },
    {
      "@type": "job",
      "@href": "/v3/job/410304463",
      "@representation": "minimal",
      "id": 410304463
    },
    {
      "@type": "job",
      "@href": "/v3/job/410304464",
      "@representation": "minimal",
      "id": 410304464
    },
    {
      "@type": "job",
      "@href": "/v3/job/410304465",
      "@representation": "minimal",
      "id": 410304465
    },
    {
      "@type": "job",
      "@href": "/v3/job/410304466",
      "@representation": "minimal",
      "id": 410304466
    }
  ],
  "stages": [

  ],
  "created_by": {
    "@type": "user",
    "@href": "/v3/user/547501",
    "@representation": "minimal",
    "id": 547501,
    "login": "asfgit"
  },
  "updated_at": "2019-04-11T07:52:28.422Z"
}