{
  "@type": "build",
  "@href": "/v3/build/414389800",
  "@representation": "standard",
  "@permissions": {
    "read": true,
    "cancel": false,
    "restart": false
  },
  "id": 414389800,
  "number": "608",
  "state": "failed",
  "duration": 1288,
  "event_type": "push",
  "previous_state": "failed",
  "pull_request_title": null,
  "pull_request_number": null,
  "started_at": "2018-08-10T06:59:39Z",
  "finished_at": "2018-08-10T07:10:29Z",
  "private": false,
  "repository": {
    "@type": "repository",
    "@href": "/v3/repo/2807812",
    "@representation": "minimal",
    "id": 2807812,
    "name": "javaparser",
    "slug": "ftomassetti/javaparser"
  },
  "branch": {
    "@type": "branch",
    "@href": "/v3/repo/2807812/branch/issue1668",
    "@representation": "minimal",
    "name": "issue1668"
  },
  "tag": null,
  "commit": {
    "@type": "commit",
    "@representation": "minimal",
    "id": 124469683,
    "sha": "67b654ca0a58b1ee50ec3d90ce4d619d4a249cf8",
    "ref": "refs/heads/issue1668",
    "message": "fix wrong check in JavassistEnumConstantDeclaration",
    "compare_url": "https://github.com/ftomassetti/javaparser/compare/0db78b116e26...67b654ca0a58",
    "committed_at": "2018-08-10T06:59:12Z"
  },
  "jobs": [
    {
      "@type": "job",
      "@href": "/v3/job/414389801",
      "@representation": "minimal",
      "id": 414389801
    },
    {
      "@type": "job",
      "@href": "/v3/job/414389802",
      "@representation": "minimal",
      "id": 414389802
    }
  ],
  "stages": [

  ],
  "created_by": {
    "@type": "user",
    "@href": "/v3/user/90605",
    "@representation": "minimal",
    "id": 90605,
    "login": "ftomassetti"
  },
  "updated_at": "2019-04-11T11:00:12.041Z"
}