{
  "@type": "build",
  "@href": "/v3/build/420513613",
  "@representation": "standard",
  "@permissions": {
    "read": true,
    "cancel": false,
    "restart": false
  },
  "id": 420513613,
  "number": "1305",
  "state": "passed",
  "duration": 3442,
  "event_type": "cron",
  "previous_state": "passed",
  "pull_request_title": null,
  "pull_request_number": null,
  "started_at": "2018-08-27T07:04:03.000Z",
  "finished_at": "2018-08-27T07:19:09.000Z",
  "private": false,
  "repository": {
    "@type": "repository",
    "@href": "/v3/repo/1834176",
    "@representation": "minimal",
    "id": 1834176,
    "name": "spring-data-examples",
    "slug": "spring-projects/spring-data-examples"
  },
  "branch": {
    "@type": "branch",
    "@href": "/v3/repo/1834176/branch/master",
    "@representation": "minimal",
    "name": "master"
  },
  "tag": null,
  "commit": {
    "@type": "commit",
    "@representation": "minimal",
    "id": 126371379,
    "sha": "dc58547743af37028466e18ef930ad0b2eef5193",
    "ref": null,
    "message": "#400 - Upgrade to Spring Boot 2.0.4.",
    "compare_url": "https://github.com/spring-projects/spring-data-examples/compare/f31c83a1f9756b920b4556383ad0e087652d8ceb...dc58547743af37028466e18ef930ad0b2eef5193",
    "committed_at": "2018-08-22T15:03:23.000Z"
  },
  "jobs": [
    {
      "@type": "job",
      "@href": "/v3/job/420513614",
      "@representation": "minimal",
      "id": 420513614
    },
    {
      "@type": "job",
      "@href": "/v3/job/420513615",
      "@representation": "minimal",
      "id": 420513615
    },
    {
      "@type": "job",
      "@href": "/v3/job/420513616",
      "@representation": "minimal",
      "id": 420513616
    },
    {
      "@type": "job",
      "@href": "/v3/job/420513617",
      "@representation": "minimal",
      "id": 420513617
    }
  ],
  "stages": [

  ],
  "created_by": {
    "@type": "user",
    "@href": "/v3/user/548917",
    "@representation": "minimal",
    "id": 548917,
    "login": "trisberg"
  },
  "updated_at": "2019-04-11T01:51:03.160Z"
}