{
  "@type": "job",
  "@href": "/v3/job/346940275",
  "@representation": "standard",
  "@permissions": {
    "read": true,
    "delete_log": false,
    "debug": false,
    "cancel": false,
    "restart": false
  },
  "id": 346940275,
  "allow_failure": false,
  "number": "11694.1",
  "state": "passed",
  "started_at": "2018-03-04T00:07:15Z",
  "finished_at": "2018-03-04T00:33:00Z",
  "build": {
    "@type": "build",
    "@href": "/v3/build/346940274",
    "@representation": "minimal",
    "id": 346940274,
    "number": "11694",
    "state": "passed",
    "duration": 3705,
    "event_type": "pull_request",
    "previous_state": "failed",
    "pull_request_title": "Danish translation",
    "pull_request_number": 4976,
    "started_at": "2018-03-04T00:07:15Z",
    "finished_at": "2018-03-04T00:33:00Z",
    "private": false
  },
  "queue": "builds.gce",
  "repository": {
    "@type": "repository",
    "@href": "/v3/repo/6039960",
    "@representation": "minimal",
    "id": 6039960,
    "name": "JMRI",
    "slug": "JMRI/JMRI"
  },
  "commit": {
    "@type": "commit",
    "@representation": "minimal",
    "id": 103202396,
    "sha": "579d1e961526087f12743c22f5c5e5bc54ee3fae",
    "ref": "refs/pull/4976/merge",
    "message": "Danish translation\n\nMore danish translation",
    "compare_url": "https://github.com/JMRI/JMRI/pull/4976",
    "committed_at": "2018-02-27T19:20:33Z"
  },
  "owner": {
    "@type": "organization",
    "@href": "/v3/org/146794",
    "@representation": "minimal",
    "id": 146794,
    "login": "JMRI"
  },
  "stage": null,
  "created_at": "2018-02-27T19:23:48.112Z",
  "updated_at": "2018-06-04T05:48:22.170Z",
  "private": false
}