{
  "@type": "job",
  "@href": "/v3/job/356142777",
  "@representation": "standard",
  "@permissions": {
    "read": true,
    "delete_log": false,
    "debug": false,
    "cancel": false,
    "restart": false
  },
  "id": 356142777,
  "allow_failure": false,
  "number": "45.1",
  "state": "failed",
  "started_at": "2018-03-21T00:46:45Z",
  "finished_at": "2018-03-21T00:51:49Z",
  "build": {
    "@type": "build",
    "@href": "/v3/build/356142776",
    "@representation": "minimal",
    "id": 356142776,
    "number": "45",
    "state": "failed",
    "duration": 304,
    "event_type": "push",
    "previous_state": "failed",
    "pull_request_title": null,
    "pull_request_number": null,
    "started_at": "2018-03-21T00:46:45Z",
    "finished_at": "2018-03-21T00:51:49Z",
    "private": false
  },
  "queue": "builds.ec2",
  "repository": {
    "@type": "repository",
    "@href": "/v3/repo/18041236",
    "@representation": "minimal",
    "id": 18041236,
    "name": "activemq-artemis",
    "slug": "clebertsuconic/activemq-artemis"
  },
  "commit": {
    "@type": "commit",
    "@representation": "minimal",
    "id": 106100069,
    "sha": "1ced33bd573dcdcf4790c909b59f3ba87c5de8c3",
    "ref": "refs/heads/footprint",
    "message": "debug",
    "compare_url": "https://github.com/clebertsuconic/activemq-artemis/compare/9ec344f60825...1ced33bd573d",
    "committed_at": "2018-03-21T00:46:31Z"
  },
  "owner": {
    "@type": "user",
    "@href": "/v3/user/617521",
    "@representation": "minimal",
    "id": 617521,
    "login": "clebertsuconic"
  },
  "stage": null,
  "created_at": "2018-03-21T00:46:42.600Z",
  "updated_at": "2018-06-04T09:22:35.207Z",
  "private": false
}