{
  "@type": "job",
  "@href": "/v3/job/246681966",
  "@representation": "standard",
  "@permissions": {
    "read": true,
    "delete_log": false,
    "debug": false,
    "cancel": false,
    "restart": false
  },
  "id": 246681966,
  "allow_failure": false,
  "number": "388.1",
  "state": "failed",
  "started_at": "2017-06-25T01:38:46Z",
  "finished_at": "2017-06-25T01:41:40Z",
  "build": {
    "@type": "build",
    "@href": "/v3/build/246681965",
    "@representation": "minimal",
    "id": 246681965,
    "number": "388",
    "state": "failed",
    "duration": 174,
    "event_type": "push",
    "previous_state": "failed",
    "pull_request_title": null,
    "pull_request_number": null,
    "started_at": "2017-06-25T01:38:46Z",
    "finished_at": "2017-06-25T01:41:40Z",
    "private": false
  },
  "queue": "builds.docker",
  "repository": {
    "@type": "repository",
    "@href": "/v3/repo/3910825",
    "@representation": "minimal",
    "id": 3910825,
    "name": "ripme",
    "slug": "4pr0n/ripme"
  },
  "commit": {
    "@type": "commit",
    "@representation": "minimal",
    "id": 71611390,
    "sha": "0e909f294855c52ed26e64126eb71f33cf2f35ea",
    "ref": "refs/heads/master",
    "message": "Update documentation and issue- and PR- templates.",
    "compare_url": "https://github.com/4pr0n/ripme/compare/4de550c8822c...0e909f294855",
    "committed_at": "2017-06-25T01:37:55Z"
  },
  "owner": {
    "@type": "user",
    "@href": "/v3/user/122695",
    "@representation": "minimal",
    "id": 122695,
    "login": "4pr0n"
  },
  "stage": null,
  "created_at": "2017-06-25T01:38:44.253Z",
  "updated_at": "2018-06-02T16:34:28.342Z",
  "private": false
}