{
  "@type": "job",
  "@href": "/v3/job/227996753",
  "@representation": "standard",
  "@permissions": {
    "read": true,
    "delete_log": false,
    "debug": false,
    "cancel": false,
    "restart": false
  },
  "id": 227996753,
  "allow_failure": false,
  "number": "1343.6",
  "state": "passed",
  "started_at": "2017-05-02T15:33:45Z",
  "finished_at": "2017-05-02T15:43:02Z",
  "build": {
    "@type": "build",
    "@href": "/v3/build/227996747",
    "@representation": "minimal",
    "id": 227996747,
    "number": "1343",
    "state": "passed",
    "duration": 3935,
    "event_type": "pull_request",
    "previous_state": "errored",
    "pull_request_title": "WIP: Support more swarm operations",
    "pull_request_number": 729,
    "started_at": "2017-05-04T01:34:04Z",
    "finished_at": "2017-05-04T01:43:31Z",
    "private": false
  },
  "queue": "builds.gce",
  "repository": {
    "@type": "repository",
    "@href": "/v3/repo/2462965",
    "@representation": "minimal",
    "id": 2462965,
    "name": "docker-client",
    "slug": "spotify/docker-client"
  },
  "commit": {
    "@type": "commit",
    "@representation": "minimal",
    "id": 65925920,
    "sha": "9c7f95e124dc306c81bc9cec0f5ec2f195d08d5e",
    "ref": "refs/pull/729/merge",
    "message": "Support more swarm operations\n\ninit, join, leave, update, unlockKey, unlock",
    "compare_url": "https://github.com/spotify/docker-client/pull/729",
    "committed_at": "2017-05-02T15:21:29Z"
  },
  "owner": {
    "@type": "organization",
    "@href": "/v3/org/9759",
    "@representation": "minimal",
    "id": 9759,
    "login": "spotify"
  },
  "stage": null,
  "created_at": "2017-05-02T15:22:11.444Z",
  "updated_at": "2018-06-02T09:15:45.191Z",
  "private": false
}